{
  "site_id": 6,
  "timestamp": "20251209_010653",
  "n_features": 28,
  "features": [
    "O3_forecast",
    "NO2_forecast",
    "T_forecast",
    "q_forecast",
    "u_forecast",
    "v_forecast",
    "w_forecast",
    "blh_forecast",
    "ratio_satellite",
    "NO2_satellite_filled",
    "HCHO_satellite_filled",
    "NO2_forecast_per_blh",
    "O3_forecast_per_blh",
    "blh_delta_1h",
    "blh_rel_change",
    "sin_hour",
    "cos_hour",
    "wind_speed",
    "wind_dir_deg",
    "wind_sector",
    "SZA_deg",
    "cosSZA",
    "solar_elevation",
    "sunset_flag",
    "solar_declination_deg",
    "hour_angle_deg",
    "solar_time_hr",
    "EoT_min"
  ],
  "O3_metrics": {
    "train_rmse": 4.389086818347775,
    "train_mae": 2.9500098319534014,
    "train_r2": 0.9708097822810735,
    "val_rmse": 13.008307984302288,
    "val_mae": 7.8359552381583315,
    "val_r2": 0.755727999577413
  },
  "NO2_metrics": {
    "train_rmse": 3.58414412702742,
    "train_mae": 2.5660130873503153,
    "train_r2": 0.9615132210074643,
    "val_rmse": 9.825149229639754,
    "val_mae": 6.73122532828616,
    "val_r2": 0.7229761099953276
  },
  "model_type": "XGBoost",
  "hyperparameters": {
    "O3": {
      "objective": "reg:squarederror",
      "n_estimators": 500,
      "max_depth": 8,
      "learning_rate": 0.05,
      "subsample": 0.8,
      "colsample_bytree": 0.8,
      "min_child_weight": 3,
      "gamma": 0.1,
      "reg_alpha": 0.1,
      "reg_lambda": 1.0,
      "random_state": 42,
      "n_jobs": -1
    },
    "NO2": {
      "objective": "reg:squarederror",
      "n_estimators": 500,
      "max_depth": 8,
      "learning_rate": 0.05,
      "subsample": 0.8,
      "colsample_bytree": 0.8,
      "min_child_weight": 3,
      "gamma": 0.1,
      "reg_alpha": 0.1,
      "reg_lambda": 1.0,
      "random_state": 42,
      "n_jobs": -1
    }
  }
}